nettyflix/__init__.py
nettyflix/models.py
nettyflix/views.py
nettyflix/db/__init__.py
nettyflix/db/csv.py
nettyflix-1.0.0.dist-info/METADATA
nettyflix-1.0.0.dist-info/WHEEL
nettyflix-1.0.0.dist-info/top_level.txt
nettyflix-1.0.0.dist-info/RECORD
