Metadata-Version: 2.1
Name: nettyflix
Version: 1.0.0
Summary: A new way to access online movies
Home-page: UNKNOWN
License: UNKNOWN
Platform: UNKNOWN
